README.md
setup.cfg
setup.py
src/dna_logger/__init__.py
src/dna_logger/logger.py
src/dna_logger/logmodel.py
src/dna_logger.egg-info/PKG-INFO
src/dna_logger.egg-info/SOURCES.txt
src/dna_logger.egg-info/dependency_links.txt
src/dna_logger.egg-info/top_level.txt
test/test_log.py