Metadata-Version: 2.1
Name: dna-logger
Version: 1.0.3
Summary: Data and Analytics Logging Module
Home-page: UNKNOWN
Author: Vishal Periyasamy Rajendran
Author-email: vishalrv1904@gmail.com
License: UNKNOWN
Platform: UNKNOWN
Requires-Python: >=3.6
